AUTHORS.rst
CONTRIBUTING.rst
HISTORY.rst
LICENSE
README.rst
kasi/AstroEventInfoService.py
kasi/LrsrCldInfoService.py
kasi/LunPhInfoService.py
kasi/RiseSetInfoService.py
kasi/SpcdeInfoService.py
kasi/SrAltudeInfoService.py
kasi/__init__.py
kasi/cli.py
kasi-0.1.3.dist-info/entry_points.txt
kasi-0.1.3.dist-info/LICENSE
kasi-0.1.3.dist-info/WHEEL
kasi-0.1.3.dist-info/METADATA
kasi-0.1.3.dist-info/RECORD
