Metadata-Version: 2.1
Name: kasi
Version: 0.1.3
Summary: KASI (Korea Astronomy and Space Science Institute) Open API Python Wrapper
Home-page: https://github.com/elbakramer/kasi
License: MIT
Author: Yunseong Hwang
Author-email: kika1492@gmail.com
Requires-Python: >=3.8,<4.0
Classifier: Development Status :: 2 - Pre-Alpha
Classifier: Intended Audience :: Developers
Classifier: License :: OSI Approved :: MIT License
Classifier: Natural Language :: English
Classifier: Programming Language :: Python :: 3
Classifier: Programming Language :: Python :: 3.8
Classifier: Programming Language :: Python :: 3.9
Provides-Extra: dev
Provides-Extra: docs
Requires-Dist: pandas (>=1.2.4,<2.0.0)
Project-URL: Bug Tracker, https://github.com/elbakramer/kasi/issues
Project-URL: Documentation, https://elbakramer.github.io/kasi/
Project-URL: Repository, https://github.com/elbakramer/kasi
